LICENSE
README.md
setup.py
pars_hitmotop.egg-info/PKG-INFO
pars_hitmotop.egg-info/SOURCES.txt
pars_hitmotop.egg-info/dependency_links.txt
pars_hitmotop.egg-info/requires.txt
pars_hitmotop.egg-info/top_level.txt
parse_hitmos/__init__.py
parse_hitmos/entered_tracks.py
parse_hitmos/excepts.py
parse_hitmos/how_to_use.py
parse_hitmos/rating_tracks_count.py
parse_hitmos/rating_tracks_page.py
parse_hitmos/config/__init__.py
parse_hitmos/config/load_data.py
parse_hitmos/tools/__init__.py
parse_hitmos/tools/base_session.py
parse_hitmos/tools/headers.py
parse_hitmos/tools/replace_symbol.py
parse_hitmos/tools/retry_func.py