Metadata-Version: 2.4
Name: pars_hitmotop
Version: 1.0.4
Home-page: https://github.com/JoyHubN/pars_hitmos
Download-URL: https://github.com/JoyHubN/pars_hitmos/arhive/v1.0.4.zip
Author: JoyHubN
Author-email: Prufu@yandex.ru
Classifier: Programming Language :: Python
Classifier: Programming Language :: Python :: 3.8
Classifier: Programming Language :: Python :: 3.9
Classifier: Programming Language :: Python :: 3.10
Classifier: Programming Language :: Python :: 3.11
Classifier: Programming Language :: Python :: Implementation :: PyPy
License-File: LICENSE
Requires-Dist: beautifulsoup4==4.13.4
Requires-Dist: fake-useragent==2.2.0
Requires-Dist: requests==2.32.4
Requires-Dist: tenacity==9.1.2
Dynamic: author
Dynamic: author-email
Dynamic: classifier
Dynamic: description
Dynamic: description-content-type
Dynamic: download-url
Dynamic: home-page
Dynamic: license-file
Dynamic: requires-dist
